gitprompter/__init__.py
gitprompter/cli.py
gitprompter/config.py
gitprompter/core.py
gitprompter/prompts.py
gitprompter/utils.py
gitprompter-0.2.0.dist-info/METADATA
gitprompter-0.2.0.dist-info/WHEEL
gitprompter-0.2.0.dist-info/entry_points.txt
gitprompter-0.2.0.dist-info/RECORD
