Metadata-Version: 2.3
Name: gitprompter
Version: 0.2.0
Summary: Генератор промтов для нейросетей на основе git diff.
Author: pasha_danilevich
Author-email: danilevitch.pasha@yandex.ru
Requires-Python: >=3.10,<4.0
Classifier: Programming Language :: Python :: 3
Classifier: Programming Language :: Python :: 3.10
Classifier: Programming Language :: Python :: 3.11
Classifier: Programming Language :: Python :: 3.12
Classifier: Programming Language :: Python :: 3.13
Requires-Dist: click (>=8.2.1,<9.0.0)
Requires-Dist: pyperclip (>=1.9.0,<2.0.0)
